dr_scaffold/__init__.py
dr_scaffold/file_api.py
dr_scaffold/generators.py
dr_scaffold/print_off.py
dr_scaffold/settings.py
dr_scaffold/management/__init__.py
dr_scaffold/management/commands/__init__.py
dr_scaffold/management/commands/dr_scaffold.py
dr_scaffold/scaffold_templates/__init__.py
dr_scaffold/scaffold_templates/admin_templates.py
dr_scaffold/scaffold_templates/app_template.py
dr_scaffold/scaffold_templates/factory_templates.py
dr_scaffold/scaffold_templates/factory_tests_templates.py
dr_scaffold/scaffold_templates/model_templates.py
dr_scaffold/scaffold_templates/serializer_templates.py
dr_scaffold/scaffold_templates/url_templates.py
dr_scaffold/scaffold_templates/view_templates.py
tests/__init__.py
tests/test_command.py
tests/test_file_api.py
tests/test_generator.py
tests/__pycache__/__init__.cpython-39-pytest-6.2.4.pyc
tests/__pycache__/__init__.cpython-39.pyc
tests/__pycache__/test_command.cpython-39-pytest-6.2.4.pyc
tests/__pycache__/test_file_api.cpython-39-pytest-6.2.4.pyc
tests/__pycache__/test_generator.cpython-39-pytest-6.2.4.pyc
dr_scaffold-2.1.2.dist-info/LICENSE
dr_scaffold-2.1.2.dist-info/METADATA
dr_scaffold-2.1.2.dist-info/WHEEL
dr_scaffold-2.1.2.dist-info/top_level.txt
dr_scaffold-2.1.2.dist-info/RECORD
